multigzip/__init__.py
multigzip/gzip.py
multigzip/gzip2.py
multigzip-0.0.2.dist-info/LICENSE
multigzip-0.0.2.dist-info/METADATA
multigzip-0.0.2.dist-info/WHEEL
multigzip-0.0.2.dist-info/top_level.txt
multigzip-0.0.2.dist-info/RECORD
