Metadata-Version: 2.1
Name: multigzip
Version: 0.0.2
Summary: Multi Member GZip Support for Python 3
Home-page: https://github.com/ClearVoice/multigzip
Author: Jeff Nappi
Author-email: jeff@clearvoice.com
License: MIT
Platform: UNKNOWN
Classifier: Programming Language :: Python :: 3
Classifier: License :: OSI Approved :: MIT License
Classifier: Operating System :: OS Independent
Provides: multigzip
